<?xml version="1.0" encoding="UTF-8"?>
<DvMCLIResult version="7.0.0-00"><CommandResult command="GetStorageArray"><StorageArray objectID="ARRAY.R601.35656" name="USP_VM@10.6.59.62" description="USP_VM (35656) at 10.6.59.62" serialNumber="35656" arrayFamily="R600" arrayType="R601" microcodeVersion="60-06-20/00" agentVersion="05_06_00" productName="RAID601" controllerVersion="60-06-21-00/00" numberOfControllers="1" capacityInGB="20058" cacheInMB="131072" sharedMemoryInMB="-1" numberOfSpareDrives="-1" freeCapacityInGB="15661" allocatedCapacityInGB="4397" hihsmCapacityInGB="0" onDemandCapacityInGB="0" totalFreeSpaceInGB="1711" largestFreeSpaceInGB="936" capacityInKB="21033182144" freeCapacityInKB="16422270784" allocatedCapacityInKB="4610911360" hihsmCapacityInKB="0" onDemandCapacityInKB="0" totalFreeSpaceInKB="1795158528" largestFreeSpaceInKB="981656064" multipathSupport="1" securityStatus="2" sequenceNumber="35656" displayArrayFamily="USP_V" displayArrayType="USP_VM" numberOfLUs="258" numberOfAllocatedLUs="96" numberOfUnallocatedLUs="111" slprStatus="0" openTotalCapacity="21033182144" openAllocatedCapacity="4610911360" openFreeCapacity="16422270784" openHiHsmCapacity="0" openOnDemandCapacity="0" imTotalCapacity="0" imAllocatedCapacity="0" imFreeCapacity="0" imHiHsmCapacity="0" imOnDemandCapacity="0" mfTotalCapacity="0" mfHiHsmCapacity="0" mfOnDemandCapacity="0" mfAllocatedCapacity="0" mfUnallocatedCapacity="0" numberOfOpenAllocatedLUs="96" numberOfOpenUnallocatedLUs="111" numberOfImAllocatedLUs="0" numberOfImUnallocatedLUs="0" numberOfMfLDEVs="0" numberOfAllocatedMfLDEVs="0" numberOfUnallocatedMfLDEVs="0" productCode="1" lastRefreshed="1297978348" autoFormatLU="1" statusOfDBInconsistency="0" configUpdateStatus="0" openAllocatedActualCapacity="20892480" openUnallocatedCapacity="3227331328" openUnallocatedActualCapacity="477632448" openReservedCapacity="13194939456" openReservedActualCapacity="13194939456" numberOfReservedLUs="51" numberOfOpenReservedLUs="51" numberOfImReservedLUs="0" distributedMode="-1" ><PortController objectID="CONTROLLER.R601.35656.1" cluster="1" card="1" controllerID="1" displayName="CHA-1G" mode="1" type="82" /><PortController objectID="CONTROLLER.R601.35656.17" cluster="2" card="1" controllerID="17" displayName="CHA-2L" mode="1" type="82" /><PortController objectID="CONTROLLER.R601.35656.18" cluster="2" card="2" controllerID="18" displayName="CHA-2K" mode="1" type="82" /><PortController objectID="CONTROLLER.R601.35656.2" cluster="1" card="2" controllerID="2" displayName="CHA-1H" mode="1" type="82" /></StorageArray><StorageArray objectID="ARRAY.R601.35657" name="USP_VM@10.6.59.52" description="USP_VM (35657) at 10.6.59.52" serialNumber="35657" arrayFamily="R600" arrayType="R601" microcodeVersion="60-06-20/00" agentVersion="05_06_00" productName="RAID601" controllerVersion="60-06-21-00/00" numberOfControllers="1" capacityInGB="24347" cacheInMB="131072" sharedMemoryInMB="-1" numberOfSpareDrives="-1" freeCapacityInGB="14024" allocatedCapacityInGB="10323" hihsmCapacityInGB="0" onDemandCapacityInGB="0" totalFreeSpaceInGB="1912" largestFreeSpaceInGB="975" capacityInKB="25530142720" freeCapacityInKB="14705477120" allocatedCapacityInKB="10824665600" hihsmCapacityInKB="0" onDemandCapacityInKB="0" totalFreeSpaceInKB="2004877824" largestFreeSpaceInKB="1023215616" multipathSupport="1" securityStatus="2" sequenceNumber="35657" displayArrayFamily="USP_V" displayArrayType="USP_VM" numberOfLUs="157" numberOfAllocatedLUs="70" numberOfUnallocatedLUs="36" slprStatus="0" openTotalCapacity="25530142720" openAllocatedCapacity="10824665600" openFreeCapacity="14705477120" openHiHsmCapacity="0" openOnDemandCapacity="0" imTotalCapacity="0" imAllocatedCapacity="0" imFreeCapacity="0" imHiHsmCapacity="0" imOnDemandCapacity="0" mfTotalCapacity="0" mfHiHsmCapacity="0" mfOnDemandCapacity="0" mfAllocatedCapacity="0" mfUnallocatedCapacity="0" numberOfOpenAllocatedLUs="70" numberOfOpenUnallocatedLUs="36" numberOfImAllocatedLUs="0" numberOfImUnallocatedLUs="0" numberOfMfLDEVs="0" numberOfAllocatedMfLDEVs="0" numberOfUnallocatedMfLDEVs="0" productCode="1" lastRefreshed="1298012505" autoFormatLU="1" statusOfDBInconsistency="0" configUpdateStatus="0" openAllocatedActualCapacity="4102435520" openUnallocatedCapacity="1510534592" openUnallocatedActualCapacity="95364672" openReservedCapacity="13194942528" openReservedActualCapacity="13194942528" numberOfReservedLUs="51" numberOfOpenReservedLUs="51" numberOfImReservedLUs="0" distributedMode="-1" ><PortController objectID="CONTROLLER.R601.35657.1" cluster="1" card="1" controllerID="1" displayName="CHA-1G" mode="1" type="82" /><PortController objectID="CONTROLLER.R601.35657.17" cluster="2" card="1" controllerID="17" displayName="CHA-2L" mode="1" type="82" /><PortController objectID="CONTROLLER.R601.35657.18" cluster="2" card="2" controllerID="18" displayName="CHA-2K" mode="1" type="82" /><PortController objectID="CONTROLLER.R601.35657.2" cluster="1" card="2" controllerID="2" displayName="CHA-1H" mode="1" type="82" /></StorageArray></CommandResult></DvMCLIResult>